xbridge/__init__.py
xbridge/__main__.py
xbridge/api.py
xbridge/converter.py
xbridge/exceptions.py
xbridge/instance.py
xbridge/modules/ae_ae_4.2.json
xbridge/modules/ae_con_cir-680-2014_2017-04-04.json
xbridge/modules/ae_con_cir-680-2014_2018-03-31.json
xbridge/modules/ae_con_its-005-2020_2021-02-28.json
xbridge/modules/ae_con_its-2013-04_2014-03-31.json
xbridge/modules/ae_con_its-2013-04_2014-07-31.json
xbridge/modules/ae_con_its-2013-04_2016-02-01.json
xbridge/modules/ae_con_its-2013-04_2016-11-15.json
xbridge/modules/ae_ind_cir-680-2014_2017-04-04.json
xbridge/modules/ae_ind_cir-680-2014_2018-03-31.json
xbridge/modules/ae_ind_its-005-2020_2021-02-28.json
xbridge/modules/ae_ind_its-2013-04_2014-03-31.json
xbridge/modules/ae_ind_its-2013-04_2014-07-31.json
xbridge/modules/ae_ind_its-2013-04_2016-02-01.json
xbridge/modules/ae_ind_its-2013-04_2016-11-15.json
xbridge/modules/ae_its-005-2020_2022-03-01.json
xbridge/modules/codis_pillar3_4.1.json
xbridge/modules/codis_pillar3_4.2.json
xbridge/modules/condis_its-2021-637_2023-05-30.json
xbridge/modules/corep_alm_con_cir-680-2014_2017-04-04.json
xbridge/modules/corep_alm_con_cir-680-2014_2018-07-31.json
xbridge/modules/corep_alm_con_cir-680-2014_2019-11-15.json
xbridge/modules/corep_alm_con_its-005-2020_2020-11-15.json
xbridge/modules/corep_alm_con_its-2014-05_2015-02-16.json
xbridge/modules/corep_alm_con_its-2015-04_2016-01-31.json
xbridge/modules/corep_alm_con_its-2016-03_2016-11-15.json
xbridge/modules/corep_alm_con_its-2016-repxx_2016-02-01.json
xbridge/modules/corep_alm_corep_4.2.json
xbridge/modules/corep_alm_ind_cir-680-2014_2017-04-04.json
xbridge/modules/corep_alm_ind_cir-680-2014_2018-07-31.json
xbridge/modules/corep_alm_ind_cir-680-2014_2019-11-15.json
xbridge/modules/corep_alm_ind_its-005-2020_2020-11-15.json
xbridge/modules/corep_alm_ind_its-2014-05_2015-02-16.json
xbridge/modules/corep_alm_ind_its-2015-04_2016-01-31.json
xbridge/modules/corep_alm_ind_its-2016-03_2016-11-15.json
eba_xbridge-1.5.0.dist-info/METADATA
eba_xbridge-1.5.0.dist-info/WHEEL
eba_xbridge-1.5.0.dist-info/entry_points.txt
eba_xbridge-1.5.0.dist-info/licenses/LICENSE
eba_xbridge-1.5.0.dist-info/RECORD
