Metadata-Version: 2.4
Name: eba-xbridge
Version: 1.5.0
Summary: XBRL-XML to XBRL-CSV converter for EBA Taxonomy (version 4.2)
License: Apache 2.0
License-File: LICENSE
Keywords: xbrl,eba,taxonomy,csv,xml
Author: MeaningfulData
Author-email: info@meaningfuldata.eu
Maintainer: Antonio Olleros
Maintainer-email: antonio.olleros@meaningfuldata.eu
Requires-Python: >=3.9
Classifier: Development Status :: 5 - Production/Stable
Classifier: Intended Audience :: Developers
Classifier: Intended Audience :: Information Technology
Classifier: Intended Audience :: Science/Research
Classifier: Programming Language :: Python :: 3
Classifier: Typing :: Typed
Requires-Dist: lxml (>=5.2.1,<6.0)
Requires-Dist: numpy (>=1.23.2,<2) ; python_version < "3.13"
Requires-Dist: numpy (>=2.1.0) ; python_version >= "3.13"
Requires-Dist: pandas (>=2.1.4,<3.0)
Project-URL: Documentation, https://docs.xbridge.meaningfuldata.eu
Project-URL: IssueTracker, https://github.com/Meaningful-Data/xbridge/issues
Project-URL: MeaningfulData, https://www.meaningfuldata.eu/
Project-URL: Repository, https://github.com/Meaningful-Data/xbridge
